memonto/__init__.py
memonto/core/__init__.py
memonto/core/configure.py
memonto/core/forget.py
memonto/core/init.py
memonto/core/recall.py
memonto/core/remember.py
memonto/core/retain.py
memonto/core/retrieve.py
memonto/llms/__init__.py
memonto/llms/anthropic.py
memonto/llms/base_llm.py
memonto/llms/openai.py
memonto/memonto.py
memonto/prompts/bisect_memory_type.prompt
memonto/prompts/chat.prompt
memonto/prompts/commit_to_memory.prompt
memonto/prompts/commit_to_memory_error_handling.prompt
memonto/prompts/expand_ontology.prompt
memonto/prompts/summarize_memory.prompt
memonto/prompts/update_memory.prompt
memonto/stores/__init__.py
memonto/stores/triple/__init__.py
memonto/stores/triple/base_store.py
memonto/stores/triple/jena.py
memonto/stores/vector/__init__.py
memonto/stores/vector/base_store.py
memonto/stores/vector/chroma.py
memonto/utils/__init__.py
memonto/utils/decorators.py
memonto/utils/exceptions.py
memonto/utils/llm.py
memonto/utils/logger.py
memonto/utils/namespaces.py
memonto/utils/rdf.py
memonto-0.2.3.dist-info/LICENSE
memonto-0.2.3.dist-info/METADATA
memonto-0.2.3.dist-info/WHEEL
memonto-0.2.3.dist-info/RECORD
