Metadata-Version: 2.1
Name: memonto
Version: 0.2.3
Summary: 
Author: shihanwan
Author-email: shihanwan@gmail.com
Requires-Python: >=3.11,<4.0
Classifier: Programming Language :: Python :: 3
Classifier: Programming Language :: Python :: 3.11
Classifier: Programming Language :: Python :: 3.12
Classifier: Programming Language :: Python :: 3.13
Requires-Dist: anthropic (>=0.34.2,<0.35.0)
Requires-Dist: black (>=24.8.0,<25.0.0)
Requires-Dist: chromadb (>=0.5.7,<0.6.0)
Requires-Dist: graphviz (>=0.20.3,<0.21.0)
Requires-Dist: loguru (>=0.7.2,<0.8.0)
Requires-Dist: openai (>=1.44.1,<2.0.0)
Requires-Dist: pydantic (>=2.9.1,<3.0.0)
Requires-Dist: pytest (>=8.3.3,<9.0.0)
Requires-Dist: rdflib (>=7.0.0,<8.0.0)
Requires-Dist: sparqlwrapper (>=2.0.0,<3.0.0)
Requires-Dist: tiktoken (>=0.7.0,<0.8.0)
